ucla_cli/__init__.py
ucla_cli/__main__.py
ucla_cli/clean.py
ucla_cli/course_titles_view.py
ucla_cli/decode.py
ucla_cli/display/__init__.py
ucla_cli/display/common.py
ucla_cli/display/kv_sections.py
ucla_cli/display/table.py
ucla_cli/extract/__init__.py
ucla_cli/extract/building_list.py
ucla_cli/extract/calendar_data.py
ucla_cli/get_course_summary.py
ucla_cli/glssd.py
ucla_cli/query/__init__.py
ucla_cli/query/building_list.py
ucla_cli/query/classroom_detail.py
ucla_cli/results.py
ucla_cli-0.0.10.dist-info/LICENSE.txt
ucla_cli-0.0.10.dist-info/METADATA
ucla_cli-0.0.10.dist-info/WHEEL
ucla_cli-0.0.10.dist-info/entry_points.txt
ucla_cli-0.0.10.dist-info/RECORD
