Metadata-Version: 2.1
Name: ucla-cli
Version: 0.0.10
Summary: 
Home-page: https://github.com/daviddavini/ucla-cli
License: MIT
Keywords: ucla,course,web-scraper,cli
Author: David Davini
Author-email: dndavini3.14@gmail.com
Requires-Python: >=3.8,<4.0
Classifier: Development Status :: 2 - Pre-Alpha
Classifier: Environment :: Console
Classifier: Intended Audience :: Developers
Classifier: Intended Audience :: End Users/Desktop
Classifier: License :: OSI Approved :: MIT License
Classifier: Operating System :: OS Independent
Classifier: Programming Language :: Python
Classifier: Programming Language :: Python :: 3
Classifier: Programming Language :: Python :: 3.8
Classifier: Programming Language :: Python :: 3.9
Classifier: Programming Language :: Python :: 3.10
Classifier: Programming Language :: Python :: 3.11
Classifier: Programming Language :: Python :: 3.12
Classifier: Programming Language :: Python :: 3.7
Classifier: Programming Language :: Python :: Implementation :: CPython
Classifier: Programming Language :: Python :: Implementation :: PyPy
Requires-Dist: beautifulsoup4 (>=4.12.3,<5.0.0)
Requires-Dist: click (>=8.1.7,<9.0.0)
Requires-Dist: requests (>=2.32.3,<3.0.0)
Requires-Dist: termcolor (>=2.4.0,<3.0.0)
Project-URL: Bug Tracker, https://github.com/daviddavini/ucla-cli/issues
Project-URL: Documentation, https://github.com/daviddavini/ucla-cli#readme
Project-URL: Repository, https://github.com/daviddavini/ucla-cli
